[
    {
        "model": "user.Worksite",
        "pk": 1,
        "fields": {
            "department": "Leonardo Spa",
            "address": "Piazza Monte Grappa 4 00195 Roma (RM)"
        }
    },
    {
        "model": "user.Worksite",
        "pk": 2,
        "fields": {
            "department": "Divisione Elicotteri",
            "address": "Località Paduni 03012 Anagni (FR)"
        }
    },
    {
        "model": "user.Worksite",
        "pk": 3,
        "fields": {
            "department": null,
            "address": "Via Giovanni Agusta 03100 Frosinone (FR)"
        }
    },
    {
        "model": "user.Worksite",
        "pk": 4,
        "fields": {
            "department": "Divisione Elettronica",
            "address": "Via dell'Industria 4 00040 Pomezia (RM)"
        }
    },
    {
        "model": "user.Worksite",
        "pk": 5,
        "fields": {
            "department": null,
            "address": "Strada Statale 148 Pontina Km 62 04100 Latina"
        }
    },
    {
        "model": "user.Worksite",
        "pk": 6,
        "fields": {
            "department": "Divisione Cyber Security",
            "address": "Via Laurentina 760 00143 Roma (RM)"
        }
    },
    {
        "model": "user.Worksite",
        "pk": 7,
        "fields": {
            "department": "Spazio",
            "address": "Via Tiburtina 965 00156 Roma (RM)"
        }
    }
]